{"cameraMode":{"drawMode":0,"name":"Shaded","section":"Shading Mode"},"sceneLighting":true,"audioPlay":false,"sceneViewState":{"m_AlwaysRefresh":false,"showFog":true,"showSkybox":true,"showFlares":true,"showImageEffects":true,"showParticleSystems":true,"showVisualEffectGraphs":true,"m_FxEnabled":true},"in2DMode":false,"pivot":{"x":-45.20640563964844,"y":-17.153806686401368,"z":-28.898605346679689},"rotation":{"x":0.06450522691011429,"y":-0.9354864954948425,"z":0.2444557547569275,"w":0.2468549758195877},"size":26.402143478393556,"orthographic":false}